py_btc_price
