Metadata-Version: 2.1
Name: py-btc-price
Version: 0.7
Summary: Get the current Bitcoin Price or Convert the fiat USD equivalente to BTC.
Home-page: https://github.com/eduardogpg/py_btc_price
Author: Eduardo Ismael García Pérez
Author-email: eduardo78d@gmail.com
License: MIT
Keywords: Criptocurrency,BTC,Bitcoin Price,BTC price
Platform: UNKNOWN
Classifier: Development Status :: 3 - Alpha
Classifier: Intended Audience :: Developers
Classifier: Topic :: Software Development :: Build Tools
Classifier: License :: OSI Approved :: MIT License
Classifier: Programming Language :: Python :: 3
